src/BarrelShifter.sv
// This made me want to blow my brains out
// Just use << and >>

module BarrelShifter #(
	parameter DATA_W = 32,
	parameter SHAMT_W = 5
) (
	input logic [DATA_W-1:0] data_in,
	input logic [SHAMT_W-1:0] shamt,
	input logic [1:0] mode,
	output logic [DATA_W-1:0] data_out
);

	logic [DATA_W-1:0] stage [SHAMT_W:0];

	always_comb begin
		stage[0] = data_in;
		for (int i = 0; i < SHAMT_W; i++) begin
			if (shamt[i]) begin
				for (int j = 0; j < DATA_W; j++) begin
					case (mode)
						2'b00: begin // logic left
							if (j >= (1 << i)) stage[i+1][j] = stage[i][j - (1<<i)];
							else stage[i+1][j] = 1'b0;
						end
						2'b01: begin // logic right
							if (j < DATA_W - (1 << i)) stage[i+1][j] = stage[i][j + (1<<i)];
							else stage[i+1][j] = 1'b0;
						end
						2'b10: begin // arithmetic right
							if (j < DATA_W - (1 << i)) stage[i+1][j] = stage[i][j + (1<<i)];
							else stage[i+1][j] = stage[i][DATA_W-1];
						end
						default: begin // Default to logic left
							if (j >= (1 << i)) stage[i+1][j] = stage[i][j - (1<<i)];
							else stage[i+1][j] = 1'b0;
						end
					endcase
				end
			end else stage[i+1] = stage[i];
		end
		data_out = stage[SHAMT_W]; 
	end
endmodule

src/dump.vcd
$version Generated by VerilatedVcd $end
$timescale 1ps $end
 $scope module TOP $end
  $var wire 32 ( data_in [31:0] $end
  $var wire 5 ) shamt [4:0] $end
  $var wire 2 * mode [1:0] $end
  $var wire 32 + data_out [31:0] $end
  $scope module BarrelShifter $end
   $var wire 32 , DATA_W [31:0] $end
   $var wire 32 - SHAMT_W [31:0] $end
   $var wire 32 ( data_in [31:0] $end
   $var wire 5 ) shamt [4:0] $end
   $var wire 2 * mode [1:0] $end
   $var wire 32 + data_out [31:0] $end
   $var wire 32 " stage[5] [31:0] $end
   $var wire 32 # stage[4] [31:0] $end
   $var wire 32 $ stage[3] [31:0] $end
   $var wire 32 % stage[2] [31:0] $end
   $var wire 32 & stage[1] [31:0] $end
   $var wire 32 ' stage[0] [31:0] $end
  $upscope $end
 $upscope $end
$enddefinitions $end


#0
b00000000000000000000000000010000 "
b00000000000000000000000000010000 #
b00000000000000000000000000010000 $
b00000000000000000000000000000001 %
b00000000000000000000000000000001 &
b00000000000000000000000000000001 '
b00000000000000000000000000000001 (
b00100 )
b00 *
b00000000000000000000000000010000 +
b00000000000000000000000000100000 ,
b00000000000000000000000000000101 -
#10
b00000000000000000000000000000011 "
b00000000000000111101000010010000 #
b00000000000000111101000010010000 $
b00000000001111010000100100000000 %
b00000000001111010000100100000000 &
b00000000001111010000100100000000 '
b00000000001111010000100100000000 (
b10100 )
b01 *
b00000000000000000000000000000011 +
#20
b11111111111111111111111111111100 "
b11111111111111000010111101110000 #
b11111111111111000010111101110000 $
b11111111110000101111011100000000 %
b11111111110000101111011100000000 &
b11111111110000101111011100000000 '
b11111111110000101111011100000000 (
b10 *
b11111111111111111111111111111100 +
#30
b00000000000000000000001000000000 "
b00000000000000000000001000000000 #
b00000000000000000000001000000000 $
b00000000000000000000000000100000 %
b00000000000000000000000000100000 &
b00000000000000000000000000010000 '
b00000000000000000000000000010000 (
b00101 )
b11 *
b00000000000000000000001000000000 +
#40
b00000000000000000000000000000000 "
b00000000000000000000000000000000 #
b00000000000000000000000000000000 $
b00000000000000000000000000000000 %
b00000000000000000000000000000000 &
b00000000000000000000000000000000 '
b00000000000000000000000000000000 (
b00 *
b00000000000000000000000000000000 +
#50
b00000000000000000000000000000001 "
b00000000000000011111111111111111 #
b00000001111111111111111111111111 $
b00011111111111111111111111111111 %
b01111111111111111111111111111111 &
b11111111111111111111111111111111 '
b11111111111111111111111111111111 (
b11111 )
b01 *
b00000000000000000000000000000001 +
#60
b10101010101010100000000000000000 "
b10101010101010101010101010101010 #
b10101010101010101010101010101010 $
b10101010101010101010101010101010 %
b10101010101010101010101010101010 &
b10101010101010101010101010101010 '
b10101010101010101010101010101010 (
b10000 )
b00 *
b10101010101010100000000000000000 +
#70
b11111111111111111111111111111111 "
b11111111111111110000000000000000 #
b11111111000000000000000000000000 $
b11110000000000000000000000000000 %
b11000000000000000000000000000000 &
b10000000000000000000000000000000 '
b10000000000000000000000000000000 (
b11111 )
b10 *
b11111111111111111111111111111111 +
